trytond/modules/akademy_dashboard/LICENSE
trytond/modules/akademy_dashboard/README.md
trytond/modules/akademy_dashboard/__init__.py
trytond/modules/akademy_dashboard/dashboard.py
trytond/modules/akademy_dashboard/dashboard.xml
trytond/modules/akademy_dashboard/menu.xml
trytond/modules/akademy_dashboard/tryton.cfg
trytond/modules/akademy_dashboard/locale/en.po
trytond/modules/akademy_dashboard/locale/fr.po
trytond/modules/akademy_dashboard/locale/pt.po
trytond/modules/akademy_dashboard/security/access_rights_admin.xml
trytond/modules/akademy_dashboard/security/access_rights_direct.xml
trytond/modules/akademy_dashboard/test/__init__.py
trytond/modules/akademy_dashboard/test/test_dashboard.py
trytond/modules/akademy_dashboard/view/action_form.xml
trytond/modules/akademy_dashboard/view/action_tree.xml
akademy_dashboard-1.1.0.dist-info/METADATA
akademy_dashboard-1.1.0.dist-info/WHEEL
akademy_dashboard-1.1.0.dist-info/licenses/LICENSE
akademy_dashboard-1.1.0.dist-info/RECORD
