Metadata-Version: 2.4
Name: akademy_dashboard
Version: 1.1.0
Summary: SAGE Education is a free and open-source project for educators, educational institutions, and governments.
Project-URL: Homepage, https://comunidadedosaber.ao
Project-URL: Documentation, https://docs.comunidadedosaber.ao
Project-URL: Demo, https://sage.comunidadedosaber.ao
Project-URL: Repository, https://github.com/zacariasjuliano/akademy-dashboard
Project-URL: Bug Tracker, https://github.com/zacariasjuliano/akademy-dashboard/issues
Project-URL: Changelog, https://github.com/zacariasjuliano/akademy-dashboard/blob/main/CHANGELOG.md
Author-email: Zacarias Juliano Capingala <zacariasjuliano@gmail.com>
License: GPL-3.0-or-later
License-File: LICENSE
Keywords: SGA,SGE,SIE,education,sage-edu,school
Requires-Python: >=3.8
Requires-Dist: akademy-classe~=1.1.0
Requires-Dist: trytond-dashboard==7.0.0
